{"@context": "http://iiif.io/api/presentation/2/context.json","@id": "https://nakamura196.github.io/dataset_tmp/collections/tanaka/image/anno/0fc5274d-3268-413b-9003-abf62990b767/p0017-annolist.json","@type": "sc:AnnotationList","resources": [{"@id": "https://nakamura196.github.io/dataset_tmp/collections/tanaka/image/anno/0fc5274d-3268-413b-9003-abf62990b767/p0017-annolist.json#1","@type": "oa:Annotation","motivation": "sc:painting","on": "https://iiif.dl.itc.u-tokyo.ac.jp/repo/iiif/0fc5274d-3268-413b-9003-abf62990b767/canvas/p17#xywh=771,501,5793,3092","resource": {"@type": "cnt:ContentAsText","chars": "和暦: 明治12年\n西暦コード: 18790099099\nタイトル: 英国発明ガラス早接の水硝子引札\n版種類: 活\n数量: 1枚\n書誌事項: 19.1×34.6　眼鏡ランプポンプ商水硝子発売元東京通油町15番地加賀屋山岸吉郎兵衛、中の挿画は溪岳画、左に「はやつぎの粉、東京山岸氏」の引札（銅、4.0×2.3）貼附あり\n内容分類: 諸営業\n帖数: 『捃拾帖』第17帖\n地名: 東京\n","format": "text/plain"}},{"@id": "https://nakamura196.github.io/dataset_tmp/collections/tanaka/image/anno/0fc5274d-3268-413b-9003-abf62990b767/p0017-annolist.json#2","@type": "oa:Annotation","motivation": "sc:painting","on": "https://iiif.dl.itc.u-tokyo.ac.jp/repo/iiif/0fc5274d-3268-413b-9003-abf62990b767/canvas/p17#xywh=3817,3634,2854,1299","resource": {"@type": "cnt:ContentAsText","chars": "和暦: 明治12年\n西暦コード: 18790099099\nタイトル: 〔板木師田中正備領取証摺物〕\n版種類: 木\n数量: 1枚\n書誌事項: 16.0×8.0　表神保町1丁目5番地板木師田中正備、但し書込みなし\n内容分類: 諸営業\n帖数: 『捃拾帖』第17帖\n地名: 東京\n","format": "text/plain"}},{"@id": "https://nakamura196.github.io/dataset_tmp/collections/tanaka/image/anno/0fc5274d-3268-413b-9003-abf62990b767/p0017-annolist.json#3","@type": "oa:Annotation","motivation": "sc:painting","on": "https://iiif.dl.itc.u-tokyo.ac.jp/repo/iiif/0fc5274d-3268-413b-9003-abf62990b767/canvas/p17#xywh=825,3526,2962,1493","resource": {"@type": "cnt:ContentAsText","chars": "和暦: 明治13年1月\n西暦コード: 18800001099\nタイトル: 〔服部長七御年玉のし袋〕\n数量: 1枚\n書誌事項: 17.0×8.0　東京京橋区銀座1丁目3番地服部長七\n内容分類: 常識・娯楽・遊戯・地図・食事\n帖数: 『捃拾帖』第17帖\n地名: 東京\n","format": "text/plain"}}]}