{"@context": "http://iiif.io/api/presentation/2/context.json","@id": "https://nakamura196.github.io/dataset_tmp/collections/tanaka/image/anno/d230f1f8-5929-4138-bb28-1108d77fd32a/p0033-annolist.json","@type": "sc:AnnotationList","resources": [{"@id": "https://nakamura196.github.io/dataset_tmp/collections/tanaka/image/anno/d230f1f8-5929-4138-bb28-1108d77fd32a/p0033-annolist.json#1","@type": "oa:Annotation","motivation": "sc:painting","on": "https://iiif.dl.itc.u-tokyo.ac.jp/repo/iiif/d230f1f8-5929-4138-bb28-1108d77fd32a/canvas/p33#xywh=4074,3471,824,828","resource": {"@type": "cnt:ContentAsText","chars": "<p>和暦: 安政5年<br/>西暦コード: 18580099099<br/>タイトル: いぎりす御油引札<br/>版種類: 木版<br/>数量: １枚<br/>書誌事項: 5.2×5.5　名古屋本町６丁目かが見や正七、「此薬油の儀ハふけをさりかみのつやをいたし、かみを黒くす、かしらのやまひを治する事大妙也」とあり<br/>形態分類: 引札<br/>内容分類: 諸営業<br/>帖数: 『捃拾帖』第1帖<br/>地名: 尾張<br/></p>","format": "text/html"}},{"@id": "https://nakamura196.github.io/dataset_tmp/collections/tanaka/image/anno/d230f1f8-5929-4138-bb28-1108d77fd32a/p0033-annolist.json#2","@type": "oa:Annotation","motivation": "sc:painting","on": "https://iiif.dl.itc.u-tokyo.ac.jp/repo/iiif/d230f1f8-5929-4138-bb28-1108d77fd32a/canvas/p33#xywh=3406,2387,598,1864","resource": {"@type": "cnt:ContentAsText","chars": "<p>和暦: 安政5年<br/>西暦コード: 18580099099<br/>タイトル: 御保命酒引札<br/>版種類: 木版<br/>数量: １枚<br/>書誌事項: 12.0×3.6　木下仁右衛門の印あり、「尾州御名酒屋大野」とあり<br/>形態分類: 引札<br/>内容分類: 諸営業<br/>帖数: 『捃拾帖』第1帖<br/>地名: 尾張<br/></p>","format": "text/html"}},{"@id": "https://nakamura196.github.io/dataset_tmp/collections/tanaka/image/anno/d230f1f8-5929-4138-bb28-1108d77fd32a/p0033-annolist.json#3","@type": "oa:Annotation","motivation": "sc:painting","on": "https://iiif.dl.itc.u-tokyo.ac.jp/repo/iiif/d230f1f8-5929-4138-bb28-1108d77fd32a/canvas/p33#xywh=3999,472,1918,2969","resource": {"@type": "cnt:ContentAsText","chars": "<p>和暦: 天保3年9月<br/>西暦コード: 18320009099<br/>タイトル: 天保四癸巳大小暦<br/>版種類: 木版<br/>数量: １枚<br/>書誌事項: 18.8×11.5　応需竜刀園弘貞、似醒樓主人酔裡謾筆、綿羊の絵に小の月を描いているもの<br/>形態分類: 暦<br/>内容分類: 引札<br/>帖数: 『捃拾帖』第1帖<br/>地名: 不明<br/></p>","format": "text/html"}},{"@id": "https://nakamura196.github.io/dataset_tmp/collections/tanaka/image/anno/d230f1f8-5929-4138-bb28-1108d77fd32a/p0033-annolist.json#4","@type": "oa:Annotation","motivation": "sc:painting","on": "https://iiif.dl.itc.u-tokyo.ac.jp/repo/iiif/d230f1f8-5929-4138-bb28-1108d77fd32a/canvas/p33#xywh=923,490,3059,1860","resource": {"@type": "cnt:ContentAsText","chars": "<p>和暦: 嘉永4年1月<br/>西暦コード: 18510001099<br/>タイトル: 嘉永辛亥太古山荘詩会掲題<br/>版種類: 木版<br/>数量: １枚<br/>書誌事項: 12.0×18.7　「荘在東山」、「会期毎月１５日」、尾張呉服街伊藤清哲拝とあり<br/>内容分類: 文芸・芸能・スポーツ・教育・出版・教化<br/>帖数: 『捃拾帖』第1帖<br/>地名: 尾張<br/></p>","format": "text/html"}},{"@id": "https://nakamura196.github.io/dataset_tmp/collections/tanaka/image/anno/d230f1f8-5929-4138-bb28-1108d77fd32a/p0033-annolist.json#5","@type": "oa:Annotation","motivation": "sc:painting","on": "https://iiif.dl.itc.u-tokyo.ac.jp/repo/iiif/d230f1f8-5929-4138-bb28-1108d77fd32a/canvas/p33#xywh=2017,2377,1392,1927","resource": {"@type": "cnt:ContentAsText","chars": "<p>和暦: 安政5年<br/>西暦コード: 18580099099<br/>タイトル: 〔尾州名古屋本町４丁目大丸下むら引札〕<br/>版種類: 木版<br/>数量: １枚<br/>書誌事項: 10.0×8.0<br/>形態分類: 引札<br/>内容分類: 諸営業<br/>帖数: 『捃拾帖』第1帖<br/>地名: 尾張<br/></p>","format": "text/html"}},{"@id": "https://nakamura196.github.io/dataset_tmp/collections/tanaka/image/anno/d230f1f8-5929-4138-bb28-1108d77fd32a/p0033-annolist.json#6","@type": "oa:Annotation","motivation": "sc:painting","on": "https://iiif.dl.itc.u-tokyo.ac.jp/repo/iiif/d230f1f8-5929-4138-bb28-1108d77fd32a/canvas/p33#xywh=891,2419,1103,1896","resource": {"@type": "cnt:ContentAsText","chars": "<p>和暦: 安政5年<br/>西暦コード: 18580099099<br/>タイトル: 呉服太物類引札<br/>版種類: 木版<br/>数量: １枚<br/>書誌事項: 9.7×7.0　他の文字判読不能<br/>形態分類: 引札<br/>内容分類: 諸営業<br/>帖数: 『捃拾帖』第1帖<br/>地名: 尾張<br/></p>","format": "text/html"}}]}