{"@context": "http://iiif.io/api/presentation/2/context.json","@id": "https://nakamura196.github.io/dataset_tmp/collections/tanaka/image/anno/de25754d-12ff-4fd4-850c-976ec5651c8d/p0028-annolist.json","@type": "sc:AnnotationList","resources": [{"@id": "https://nakamura196.github.io/dataset_tmp/collections/tanaka/image/anno/de25754d-12ff-4fd4-850c-976ec5651c8d/p0028-annolist.json#1","@type": "oa:Annotation","motivation": "sc:painting","on": "https://iiif.dl.itc.u-tokyo.ac.jp/repo/iiif/de25754d-12ff-4fd4-850c-976ec5651c8d/canvas/p28#xywh=1065,706,2386,2106","resource": {"@type": "cnt:ContentAsText","chars": "和暦: 明治4?年\n西暦コード: 18710199099\nタイトル: 東京名所十二勝景\n版種類: 銅版\n数量: １枚\n書誌事項: 12.1×14.3　於東京玄玄堂鐫、梅屋敷庭、三圍春堤、梅社雪中、不忍蓮池、品川冲中、柳島妙見、亀戸天神、日本橋秋、吉原春色、両国夏日、浅草酉町、首尾松月\n内容分類: 常識・娯楽・遊戯・地図・食事\n帖数: 『捃拾帖』第13帖\n地名: 東京\n","format": "text/plain"}},{"@id": "https://nakamura196.github.io/dataset_tmp/collections/tanaka/image/anno/de25754d-12ff-4fd4-850c-976ec5651c8d/p0028-annolist.json#2","@type": "oa:Annotation","motivation": "sc:painting","on": "https://iiif.dl.itc.u-tokyo.ac.jp/repo/iiif/de25754d-12ff-4fd4-850c-976ec5651c8d/canvas/p28#xywh=3769,887,2934,4077","resource": {"@type": "cnt:ContentAsText","chars": "和暦: 明治5年1月20日\n西暦コード: 18720001020\nタイトル: 官版銅刻官等表\n版種類: 銅版\n数量: １枚\n書誌事項: 25.0×18.2　御用御書物師東京芝神明前三島町和泉屋市兵衛発行、水鳥舎江嶋舟霞斎鐫、包紙（9.0×6.5）あり\n内容分類: 政治社会変動\n帖数: 『捃拾帖』第13帖\n地名: 東京\n","format": "text/plain"}},{"@id": "https://nakamura196.github.io/dataset_tmp/collections/tanaka/image/anno/de25754d-12ff-4fd4-850c-976ec5651c8d/p0028-annolist.json#3","@type": "oa:Annotation","motivation": "sc:painting","on": "https://iiif.dl.itc.u-tokyo.ac.jp/repo/iiif/de25754d-12ff-4fd4-850c-976ec5651c8d/canvas/p28#xywh=957,2740,2633,2053","resource": {"@type": "cnt:ContentAsText","chars": "和暦: 明治4?年\n西暦コード: 18710199099\nタイトル: 東京神田上水御茶水真写図\n版種類: 銅版\n数量: １枚\n書誌事項: 11.9×15.9　玄々堂松田緑山鐫\n内容分類: 常識・娯楽・遊戯・地図・食事\n帖数: 『捃拾帖』第13帖\n地名: 東京\n","format": "text/plain"}}]}