{"@context": "http://iiif.io/api/presentation/2/context.json","@id": "https://nakamura196.github.io/dataset_tmp/collections/tanaka/image/anno/dc100a27-bdd9-47f1-8d55-ecc0c1f6db1f/p0062-annolist.json","@type": "sc:AnnotationList","resources": [{"@id": "https://nakamura196.github.io/dataset_tmp/collections/tanaka/image/anno/dc100a27-bdd9-47f1-8d55-ecc0c1f6db1f/p0062-annolist.json#1","@type": "oa:Annotation","motivation": "sc:painting","on": "https://iiif.dl.itc.u-tokyo.ac.jp/repo/iiif/dc100a27-bdd9-47f1-8d55-ecc0c1f6db1f/canvas/p62#xywh=4663,2658,1444,1907","resource": {"@type": "cnt:ContentAsText","chars": "和暦: 文久2?年\n西暦コード: 18620199099\nタイトル: 根元たん切宇寿飴引札\n版種類: 木版\n数量: １枚\n書誌事項: 11.2×9.7　元飯田町中坂上柏屋国五郎\n形態分類: 引札\n内容分類: 病気・医療\n帖数: 『捃拾帖』第4帖\n地名: 江戸\n","format": "text/plain"}},{"@id": "https://nakamura196.github.io/dataset_tmp/collections/tanaka/image/anno/dc100a27-bdd9-47f1-8d55-ecc0c1f6db1f/p0062-annolist.json#2","@type": "oa:Annotation","motivation": "sc:painting","on": "https://iiif.dl.itc.u-tokyo.ac.jp/repo/iiif/dc100a27-bdd9-47f1-8d55-ecc0c1f6db1f/canvas/p62#xywh=3738,517,827,2242","resource": {"@type": "cnt:ContentAsText","chars": "和暦: 文久2?年\n西暦コード: 18620199099\nタイトル: 雪の梅引札\n版種類: 木版\n数量: １枚\n書誌事項: 13.7×4.6　小石川茶師茗荷屋与兵衛、茶の品名か\n形態分類: 引札\n内容分類: 諸営業\n帖数: 『捃拾帖』第4帖\n地名: 江戸\n","format": "text/plain"}},{"@id": "https://nakamura196.github.io/dataset_tmp/collections/tanaka/image/anno/dc100a27-bdd9-47f1-8d55-ecc0c1f6db1f/p0062-annolist.json#3","@type": "oa:Annotation","motivation": "sc:painting","on": "https://iiif.dl.itc.u-tokyo.ac.jp/repo/iiif/dc100a27-bdd9-47f1-8d55-ecc0c1f6db1f/canvas/p62#xywh=3838,3383,800,1208","resource": {"@type": "cnt:ContentAsText","chars": "和暦: 文久2?年\n西暦コード: 18620199099\nタイトル: 〔市川新車似顔絵〕\n版種類: 木版\n数量: １枚\n書誌事項: 6.9×3.8　「新車これからがかんじんかなめさ」とあり\n内容分類: 芝居・浄瑠璃・歌謡\n帖数: 『捃拾帖』第4帖\n地名: 江戸\n","format": "text/plain"}},{"@id": "https://nakamura196.github.io/dataset_tmp/collections/tanaka/image/anno/dc100a27-bdd9-47f1-8d55-ecc0c1f6db1f/p0062-annolist.json#4","@type": "oa:Annotation","motivation": "sc:painting","on": "https://iiif.dl.itc.u-tokyo.ac.jp/repo/iiif/dc100a27-bdd9-47f1-8d55-ecc0c1f6db1f/canvas/p62#xywh=3892,2821,628,573","resource": {"@type": "cnt:ContentAsText","chars": "和暦: 文久2?年\n西暦コード: 18620199099\nタイトル: 〔本郷２丁目大横町大清引札〕\n版種類: 木版\n数量: １枚\n書誌事項: 3.8×3.8\n形態分類: 引札\n内容分類: 諸営業\n帖数: 『捃拾帖』第4帖\n地名: 江戸\n","format": "text/plain"}},{"@id": "https://nakamura196.github.io/dataset_tmp/collections/tanaka/image/anno/dc100a27-bdd9-47f1-8d55-ecc0c1f6db1f/p0062-annolist.json#5","@type": "oa:Annotation","motivation": "sc:painting","on": "https://iiif.dl.itc.u-tokyo.ac.jp/repo/iiif/dc100a27-bdd9-47f1-8d55-ecc0c1f6db1f/canvas/p62#xywh=981,853,2532,3603","resource": {"@type": "cnt:ContentAsText","chars": "和暦: 文久2?年\n西暦コード: 18620199099\nタイトル: 元祖雁皮紙目録\n版種類: 木版\n数量: １枚\n書誌事項: 24.5×33.0　豆州熱海今井半太夫製、江戸日本橋通４町目金花堂須原屋佐助、紙の種類が詳細に書かれている\n形態分類: 引札\n内容分類: 諸営業\n帖数: 『捃拾帖』第4帖\n地名: 江戸\n","format": "text/plain"}},{"@id": "https://nakamura196.github.io/dataset_tmp/collections/tanaka/image/anno/dc100a27-bdd9-47f1-8d55-ecc0c1f6db1f/p0062-annolist.json#6","@type": "oa:Annotation","motivation": "sc:painting","on": "https://iiif.dl.itc.u-tokyo.ac.jp/repo/iiif/dc100a27-bdd9-47f1-8d55-ecc0c1f6db1f/canvas/p62#xywh=4483,533,1642,2179","resource": {"@type": "cnt:ContentAsText","chars": "和暦: 文久2?年\n西暦コード: 18620199099\nタイトル: 〔日本橋通３丁目三ツ喜屋寿美三そめ粉てぐす唐物類引札〕\n版種類: 木版\n数量: １枚\n書誌事項: 13.2×10.0\n形態分類: 引札\n内容分類: 諸営業\n帖数: 『捃拾帖』第4帖\n地名: 江戸\n","format": "text/plain"}}]}